dictionary/__init__.py
dictionary/dictionary.py
very_simple_dictionary-2.2.0.dist-info/METADATA
very_simple_dictionary-2.2.0.dist-info/WHEEL
very_simple_dictionary-2.2.0.dist-info/top_level.txt
very_simple_dictionary-2.2.0.dist-info/RECORD
