Metadata-Version: 2.1
Name: very-simple-dictionary
Version: 2.2.0
Summary: UNKNOWN
Author: Emre Sülün
License: UNKNOWN
Platform: UNKNOWN
Requires-Python: >=3.8
Requires-Dist: requests (>=2.23.0)
